Metadata-Version: 1.0
Name: distribution-gaussian-binomial
Version: 0.1
Summary: Gaussian and Binomial distributions
Home-page: UNKNOWN
Author: Shubhadip De
Author-email: shubho.dae@gmail.com
License: UNKNOWN
Platform: UNKNOWN
